{"id":2988725,"archive_url":"https://api.github.com/repos/nuxeo/nuxeo-services/{archive_format}{/ref}","fork":false,"mirror_url":null,"svn_url":"https://github.com/nuxeo/nuxeo-services","html_url":"https://github.com/nuxeo/nuxeo-services","subscribers_url":"https://api.github.com/repos/nuxeo/nuxeo-services/subscribers","forks_count":4,"language":"Java","description":"Nuxeo Services","blobs_url":"https://api.github.com/repos/nuxeo/nuxeo-services/git/blobs{/sha}","default_branch":"master","updated_at":"2013-01-29T17:32:28Z","teams_url":"https://api.github.com/repos/nuxeo/nuxeo-services/teams","organization":{"type":"Organization","url":"https://api.github.com/users/nuxeo","events_url":"https://api.github.com/users/nuxeo/events{/privacy}","repos_url":"https://api.github.com/users/nuxeo/repos","organizations_url":"https://api.github.com/users/nuxeo/orgs","login":"nuxeo","received_events_url":"https://api.github.com/users/nuxeo/received_events","starred_url":"https://api.github.com/users/nuxeo/starred{/owner}{/repo}","gravatar_id":"190285ad93689e38c39692eb36033a10","followers_url":"https://api.github.com/users/nuxeo/followers","following_url":"https://api.github.com/users/nuxeo/following","avatar_url":"https://secure.gravatar.com/avatar/190285ad93689e38c39692eb36033a10?d=https://a248.e.akamai.net/assets.github.com%2Fimages%2Fgravatars%2Fgravatar-org-420.png","subscriptions_url":"https://api.github.com/users/nuxeo/subscriptions","id":460607,"gists_url":"https://api.github.com/users/nuxeo/gists{/gist_id}"},"homepage":"","keys_url":"https://api.github.com/repos/nuxeo/nuxeo-services/keys{/key_id}","merges_url":"https://api.github.com/repos/nuxeo/nuxeo-services/merges","has_issues":false,"downloads_url":"https://api.github.com/repos/nuxeo/nuxeo-services/downloads","ssh_url":"git@github.com:nuxeo/nuxeo-services.git","clone_url":"https://github.com/nuxeo/nuxeo-services.git","languages_url":"https://api.github.com/repos/nuxeo/nuxeo-services/languages","statuses_url":"https://api.github.com/repos/nuxeo/nuxeo-services/statuses/{sha}","watchers":4,"branches_url":"https://api.github.com/repos/nuxeo/nuxeo-services/branches{/branch}","issue_comment_url":"https://api.github.com/repos/nuxeo/nuxeo-services/issues/comments/{number}","issues_url":"https://api.github.com/repos/nuxeo/nuxeo-services/issues{/number}","permissions":{"push":true,"pull":true,"admin":true},"collaborators_url":"https://api.github.com/repos/nuxeo/nuxeo-services/collaborators{/collaborator}","watchers_count":4,"has_wiki":true,"compare_url":"https://api.github.com/repos/nuxeo/nuxeo-services/compare/{base}...{head}","commits_url":"https://api.github.com/repos/nuxeo/nuxeo-services/commits{/sha}","contents_url":"https://api.github.com/repos/nuxeo/nuxeo-services/contents/{+path}","tags_url":"https://api.github.com/repos/nuxeo/nuxeo-services/tags{/tag}","contributors_url":"https://api.github.com/repos/nuxeo/nuxeo-services/contributors","trees_url":"https://api.github.com/repos/nuxeo/nuxeo-services/git/trees{/sha}","assignees_url":"https://api.github.com/repos/nuxeo/nuxeo-services/assignees{/user}","open_issues_count":0,"private":false,"git_url":"git://github.com/nuxeo/nuxeo-services.git","url":"https://api.github.com/repos/nuxeo/nuxeo-services","events_url":"https://api.github.com/repos/nuxeo/nuxeo-services/events","git_commits_url":"https://api.github.com/repos/nuxeo/nuxeo-services/git/commits{/sha}","pushed_at":"2013-01-29T17:31:36Z","name":"nuxeo-services","git_refs_url":"https://api.github.com/repos/nuxeo/nuxeo-services/git/refs{/sha}","notifications_url":"https://api.github.com/repos/nuxeo/nuxeo-services/notifications{?since,all,participating}","forks":4,"master_branch":"master","size":528,"stargazers_url":"https://api.github.com/repos/nuxeo/nuxeo-services/stargazers","issue_events_url":"https://api.github.com/repos/nuxeo/nuxeo-services/issues/events{/number}","has_downloads":true,"full_name":"nuxeo/nuxeo-services","labels_url":"https://api.github.com/repos/nuxeo/nuxeo-services/labels{/name}","comments_url":"https://api.github.com/repos/nuxeo/nuxeo-services/comments{/number}","pulls_url":"https://api.github.com/repos/nuxeo/nuxeo-services/pulls{/number}","network_count":4,"subscription_url":"https://api.github.com/repos/nuxeo/nuxeo-services/subscription","created_at":"2011-12-15T16:03:53Z","forks_url":"https://api.github.com/repos/nuxeo/nuxeo-services/forks","git_tags_url":"https://api.github.com/repos/nuxeo/nuxeo-services/git/tags{/sha}","milestones_url":"https://api.github.com/repos/nuxeo/nuxeo-services/milestones{/number}","open_issues":0,"hooks_url":"https://api.github.com/repos/nuxeo/nuxeo-services/hooks","owner":{"type":"Organization","url":"https://api.github.com/users/nuxeo","events_url":"https://api.github.com/users/nuxeo/events{/privacy}","repos_url":"https://api.github.com/users/nuxeo/repos","organizations_url":"https://api.github.com/users/nuxeo/orgs","login":"nuxeo","received_events_url":"https://api.github.com/users/nuxeo/received_events","starred_url":"https://api.github.com/users/nuxeo/starred{/owner}{/repo}","gravatar_id":"190285ad93689e38c39692eb36033a10","followers_url":"https://api.github.com/users/nuxeo/followers","following_url":"https://api.github.com/users/nuxeo/following","avatar_url":"https://secure.gravatar.com/avatar/190285ad93689e38c39692eb36033a10?d=https://a248.e.akamai.net/assets.github.com%2Fimages%2Fgravatars%2Fgravatar-org-420.png","subscriptions_url":"https://api.github.com/users/nuxeo/subscriptions","id":460607,"gists_url":"https://api.github.com/users/nuxeo/gists{/gist_id}"}}