{"id":2988709,"has_issues":false,"fork":false,"issue_comment_url":"https://api.github.com/repos/nuxeo/nuxeo-features/issues/comments/{number}","issues_url":"https://api.github.com/repos/nuxeo/nuxeo-features/issues{/number}","hooks_url":"https://api.github.com/repos/nuxeo/nuxeo-features/hooks","mirror_url":null,"svn_url":"https://github.com/nuxeo/nuxeo-features","archive_url":"https://api.github.com/repos/nuxeo/nuxeo-features/{archive_format}{/ref}","homepage":"","forks_count":4,"subscribers_url":"https://api.github.com/repos/nuxeo/nuxeo-features/subscribers","compare_url":"https://api.github.com/repos/nuxeo/nuxeo-features/compare/{base}...{head}","blobs_url":"https://api.github.com/repos/nuxeo/nuxeo-features/git/blobs{/sha}","contributors_url":"https://api.github.com/repos/nuxeo/nuxeo-features/contributors","teams_url":"https://api.github.com/repos/nuxeo/nuxeo-features/teams","url":"https://api.github.com/repos/nuxeo/nuxeo-features","has_downloads":true,"master_branch":"master","created_at":"2011-12-15T16:02:25Z","keys_url":"https://api.github.com/repos/nuxeo/nuxeo-features/keys{/key_id}","merges_url":"https://api.github.com/repos/nuxeo/nuxeo-features/merges","open_issues_count":0,"tags_url":"https://api.github.com/repos/nuxeo/nuxeo-features/tags{/tag}","statuses_url":"https://api.github.com/repos/nuxeo/nuxeo-features/statuses/{sha}","permissions":{"push":true,"admin":true,"pull":true},"branches_url":"https://api.github.com/repos/nuxeo/nuxeo-features/branches{/branch}","collaborators_url":"https://api.github.com/repos/nuxeo/nuxeo-features/collaborators{/collaborator}","watchers_count":5,"stargazers_url":"https://api.github.com/repos/nuxeo/nuxeo-features/stargazers","labels_url":"https://api.github.com/repos/nuxeo/nuxeo-features/labels{/name}","updated_at":"2013-01-02T17:52:42Z","contents_url":"https://api.github.com/repos/nuxeo/nuxeo-features/contents/{+path}","trees_url":"https://api.github.com/repos/nuxeo/nuxeo-features/git/trees{/sha}","commits_url":"https://api.github.com/repos/nuxeo/nuxeo-features/commits{/sha}","private":false,"assignees_url":"https://api.github.com/repos/nuxeo/nuxeo-features/assignees{/user}","milestones_url":"https://api.github.com/repos/nuxeo/nuxeo-features/milestones{/number}","watchers":5,"git_url":"git://github.com/nuxeo/nuxeo-features.git","ssh_url":"git@github.com:nuxeo/nuxeo-features.git","notifications_url":"https://api.github.com/repos/nuxeo/nuxeo-features/notifications{?since,all,participating}","full_name":"nuxeo/nuxeo-features","name":"nuxeo-features","pushed_at":"2013-01-02T17:52:41Z","events_url":"https://api.github.com/repos/nuxeo/nuxeo-features/events","git_commits_url":"https://api.github.com/repos/nuxeo/nuxeo-features/git/commits{/sha}","clone_url":"https://github.com/nuxeo/nuxeo-features.git","size":848,"open_issues":0,"forks":4,"git_refs_url":"https://api.github.com/repos/nuxeo/nuxeo-features/git/refs{/sha}","has_wiki":false,"issue_events_url":"https://api.github.com/repos/nuxeo/nuxeo-features/issues/events{/number}","html_url":"https://github.com/nuxeo/nuxeo-features","comments_url":"https://api.github.com/repos/nuxeo/nuxeo-features/comments{/number}","pulls_url":"https://api.github.com/repos/nuxeo/nuxeo-features/pulls{/number}","organization":{"type":"Organization","events_url":"https://api.github.com/users/nuxeo/events{/privacy}","repos_url":"https://api.github.com/users/nuxeo/repos","login":"nuxeo","subscriptions_url":"https://api.github.com/users/nuxeo/subscriptions","received_events_url":"https://api.github.com/users/nuxeo/received_events","starred_url":"https://api.github.com/users/nuxeo/starred{/owner}{/repo}","gists_url":"https://api.github.com/users/nuxeo/gists{/gist_id}","url":"https://api.github.com/users/nuxeo","followers_url":"https://api.github.com/users/nuxeo/followers","following_url":"https://api.github.com/users/nuxeo/following","avatar_url":"https://secure.gravatar.com/avatar/190285ad93689e38c39692eb36033a10?d=https://a248.e.akamai.net/assets.github.com%2Fimages%2Fgravatars%2Fgravatar-org-420.png","organizations_url":"https://api.github.com/users/nuxeo/orgs","id":460607,"gravatar_id":"190285ad93689e38c39692eb36033a10"},"subscription_url":"https://api.github.com/repos/nuxeo/nuxeo-features/subscription","downloads_url":"https://api.github.com/repos/nuxeo/nuxeo-features/downloads","description":"Nuxeo Features","network_count":4,"git_tags_url":"https://api.github.com/repos/nuxeo/nuxeo-features/git/tags{/sha}","language":"Java","forks_url":"https://api.github.com/repos/nuxeo/nuxeo-features/forks","languages_url":"https://api.github.com/repos/nuxeo/nuxeo-features/languages","owner":{"type":"Organization","events_url":"https://api.github.com/users/nuxeo/events{/privacy}","repos_url":"https://api.github.com/users/nuxeo/repos","login":"nuxeo","subscriptions_url":"https://api.github.com/users/nuxeo/subscriptions","received_events_url":"https://api.github.com/users/nuxeo/received_events","starred_url":"https://api.github.com/users/nuxeo/starred{/owner}{/repo}","gists_url":"https://api.github.com/users/nuxeo/gists{/gist_id}","url":"https://api.github.com/users/nuxeo","followers_url":"https://api.github.com/users/nuxeo/followers","following_url":"https://api.github.com/users/nuxeo/following","avatar_url":"https://secure.gravatar.com/avatar/190285ad93689e38c39692eb36033a10?d=https://a248.e.akamai.net/assets.github.com%2Fimages%2Fgravatars%2Fgravatar-org-420.png","organizations_url":"https://api.github.com/users/nuxeo/orgs","id":460607,"gravatar_id":"190285ad93689e38c39692eb36033a10"}}